{
	"version": "1.0.0",
	"description": "This is Entry point Input Data Type, which is dynamic datatype, The parameter names will be populated during the Design time for each inputs",
	"properties": {
		"type": {
			"required": true,
			"type": "string"
		},
		"description": {
			"required": false,
			"type": "string"
		},
		"required": {
			"required": false,
			"type": "boolean"
		},
		"default": {
			"required": false,
			"type": "string"
		},
		"entry_schema": {
			"required": false,
			"type": "string"
		}
	},
	"derived_from": "tosca.datatypes.Root"
}